rope_mcp/__init__.py
rope_mcp/config.py
rope_mcp/pyright_client.py
rope_mcp/rope_client.py
rope_mcp/server.py
rope_mcp/lsp/__init__.py
rope_mcp/lsp/client.py
rope_mcp/lsp/types.py
rope_mcp/tools/__init__.py
rope_mcp/tools/change_signature.py
rope_mcp/tools/completions.py
rope_mcp/tools/definition.py
rope_mcp/tools/diagnostics.py
rope_mcp/tools/hover.py
rope_mcp/tools/move.py
rope_mcp/tools/references.py
rope_mcp/tools/rename.py
rope_mcp/tools/search.py
rope_mcp/tools/symbols.py
python_lsp_mcp-0.3.0.dist-info/METADATA
python_lsp_mcp-0.3.0.dist-info/WHEEL
python_lsp_mcp-0.3.0.dist-info/entry_points.txt
python_lsp_mcp-0.3.0.dist-info/RECORD
