Metadata-Version: 2.4
Name: python-lsp-mcp
Version: 0.3.0
Summary: MCP server providing Python code analysis using Rope and Pyright
Project-URL: Homepage, https://github.com/pinylin/pyright-mcp
Project-URL: Repository, https://github.com/pinylin/pyright-mcp
Project-URL: Documentation, https://github.com/pinylin/pyright-mcp#readme
Author: treedy
License-Expression: MIT
Keywords: ai,claude,code-intelligence,lsp,mcp,pyright,python,refactoring,rope,type-checking
Classifier: Development Status :: 4 - Beta
Classifier: Intended Audience :: Developers
Classifier: License :: OSI Approved :: MIT License
Classifier: Programming Language :: Python :: 3
Classifier: Programming Language :: Python :: 3.10
Classifier: Programming Language :: Python :: 3.11
Classifier: Programming Language :: Python :: 3.12
Classifier: Programming Language :: Python :: 3.13
Classifier: Topic :: Software Development :: Libraries :: Python Modules
Classifier: Topic :: Text Editors :: Integrated Development Environments (IDE)
Requires-Python: >=3.10
Requires-Dist: mcp>=1.0.0
Requires-Dist: rope>=1.13.0
Requires-Dist: tomli>=2.0.0; python_version < '3.11'
Provides-Extra: dev
Requires-Dist: pytest>=8.0.0; extra == 'dev'
Requires-Dist: ruff>=0.4.0; extra == 'dev'
Requires-Dist: watchdog>=4.0.0; extra == 'dev'
